{"NIFTY 50": {"date": "2026-05-25", "open": 23940.25, "high": 24054.45, "low": 23922.85, "close": 24031.7, "volume": 0}, "NIFTY NEXT 50": {"date": "2026-05-25", "open": 70444.05, "high": 70909.75, "low": 70390.9, "close": 70815.85, "volume": 0}, "NIFTY 100": {"date": "2026-05-25", "open": 24899.85, "high": 25025.6, "low": 24883.1, "close": 25001.7, "volume": 0}, "NIFTY 200": {"date": "2026-05-25", "open": 13803.2, "high": 13862.55, "low": 13794.5, "close": 13849.1, "volume": 0}, "NIFTY 500": {"date": "2026-05-25", "open": 22859.5, "high": 22949.95, "low": 22849.1, "close": 22929.45, "volume": 0}, "NIFTY MIDCAP 50": {"date": "2026-05-25", "open": 17637.85, "high": 17672.3, "low": 17588.4, "close": 17650.6, "volume": 0}, "NIFTY MIDCAP 100": {"date": "2026-05-25", "open": 61952.45, "high": 62034.7, "low": 61777.0, "close": 61966.6, "volume": 0}, "NIFTY SMALLCAP 100": {"date": "2026-05-25", "open": 18130.2, "high": 18216.85, "low": 18118.55, "close": 18202.7, "volume": 0}, "NIFTY AUTO": {"date": "2026-05-25", "open": 26400.45, "high": 26655.6, "low": 26319.6, "close": 26463.05, "volume": 0}, "NIFTY BANK": {"date": "2026-05-25", "open": 54610.55, "high": 55405.2, "low": 54590.7, "close": 55293.65, "volume": 0}, "NIFTY ENERGY": {"date": "2026-05-25", "open": 40609.15, "high": 40689.4, "low": 40387.45, "close": 40578.8, "volume": 0}, "NIFTY FINANCIAL SERVICES": {"date": "2026-05-25", "open": 25805.8, "high": 26145.75, "low": 25797.95, "close": 26102.15, "volume": 0}, "NIFTY FMCG": {"date": "2026-05-25", "open": 50572.8, "high": 50721.1, "low": 50062.15, "close": 50157.75, "volume": 0}, "NIFTY IT": {"date": "2026-05-25", "open": 29103.65, "high": 29177.8, "low": 28831.3, "close": 28979.85, "volume": 0}, "NIFTY MEDIA": {"date": "2026-05-25", "open": 1387.75, "high": 1398.8, "low": 1374.5, "close": 1378.45, "volume": 0}, "NIFTY METAL": {"date": "2026-05-25", "open": 13355.7, "high": 13385.85, "low": 13271.65, "close": 13345.65, "volume": 0}, "NIFTY MNC": {"date": "2026-05-25", "open": 32209.55, "high": 32276.15, "low": 31992.05, "close": 32058.2, "volume": 0}, "NIFTY PHARMA": {"date": "2026-05-25", "open": 24615.15, "high": 24762.9, "low": 24543.75, "close": 24674.7, "volume": 0}, "NIFTY PSU BANK": {"date": "2026-05-25", "open": 8102.4, "high": 8258.05, "low": 8093.25, "close": 8238.1, "volume": 0}, "NIFTY REALTY": {"date": "2026-05-25", "open": 783.1, "high": 787.4, "low": 780.8, "close": 786.05, "volume": 0}, "NIFTY INDIA CONSUMPTION": {"date": "2026-05-25", "open": 11427.75, "high": 11456.95, "low": 11376.1, "close": 11414.15, "volume": 0}, "NIFTY COMMODITIES": {"date": "2026-05-25", "open": 10329.75, "high": 10356.3, "low": 10272.6, "close": 10345.5, "volume": 0}, "NIFTY DIVIDEND OPPORTUNITIES 50": {"date": "2026-05-25", "open": 5949.9, "high": 5954.85, "low": 5925.5, "close": 5938.5, "volume": 0}, "NIFTY INFRASTRUCTURE": {"date": "2026-05-25", "open": 9460.8, "high": 9471.85, "low": 9425.3, "close": 9460.2, "volume": 0}, "NIFTY PSE": {"date": "2026-05-25", "open": 10473.5, "high": 10493.35, "low": 10420.7, "close": 10481.95, "volume": 0}, "NIFTY SERVICES SECTOR": {"date": "2026-05-25", "open": 30222.2, "high": 30426.05, "low": 30193.85, "close": 30388.0, "volume": 0}, "NIFTY50 SHARIAH": {"date": "2026-05-25", "open": 4367.15, "high": 4370.05, "low": 4339.15, "close": 4343.2, "volume": 0}, "NIFTY500 SHARIAH": {"date": "2026-05-25", "open": 6927.75, "high": 6930.05, "low": 6897.05, "close": 6908.45, "volume": 0}, "NIFTY LOW VOLATILITY 50": {"date": "2026-05-25", "open": 24469.3, "high": 24508.25, "low": 24395.0, "close": 24438.05, "volume": 0}, "NIFTY ALPHA 50": {"date": "2026-05-25", "open": 52692.45, "high": 52974.85, "low": 52612.0, "close": 52873.3, "volume": 0}, "NIFTY HIGH BETA 50": {"date": "2026-05-25", "open": 4197.85, "high": 4219.25, "low": 4187.35, "close": 4214.6, "volume": 0}, "NIFTY100 EQUAL WEIGHT": {"date": "2026-05-25", "open": 34028.45, "high": 34185.2, "low": 34000.4, "close": 34148.8, "volume": 0}, "NIFTY100 LIQUID 15": {"date": "2026-05-25", "open": 7177.35, "high": 7223.95, "low": 7164.5, "close": 7215.25, "volume": 0}, "NIFTY CPSE": {"date": "2026-05-25", "open": 7198.75, "high": 7198.8, "low": 7137.1, "close": 7156.65, "volume": 0}, "NIFTY50 VALUE 20": {"date": "2026-05-25", "open": 12105.75, "high": 12144.5, "low": 12071.0, "close": 12129.95, "volume": 0}, "NIFTY MIDCAP LIQUID 15": {"date": "2026-05-25", "open": 16833.3, "high": 16908.75, "low": 16771.3, "close": 16881.4, "volume": 0}, "NIFTY SHARIAH 25": {"date": "2026-05-25", "open": 7869.9, "high": 7871.4, "low": 7829.75, "close": 7841.65, "volume": 0}, "INDIA VIX": {"date": "2026-05-25", "open": 17.91, "high": 17.91, "low": 16.3925, "close": 16.7, "volume": 0}, "NIFTY GROWTH SECTORS 15": {"date": "2026-05-25", "open": 10902.9, "high": 10933.2, "low": 10874.9, "close": 10891.25, "volume": 0}, "NIFTY50 TR 1X INVERSE": {"date": "2026-05-25", "open": 179.6, "high": 179.7, "low": 178.7, "close": 178.9, "volume": 0}, "NIFTY50 TR 2X LEVERAGE": {"date": "2026-05-25", "open": 17979.15, "high": 18149.0, "low": 17955.6, "close": 18115.25, "volume": 0}, "NIFTY50 PR 1X INVERSE": {"date": "2026-05-25", "open": 220.0, "high": 220.15, "low": 218.95, "close": 219.15, "volume": 0}, "NIFTY50 PR 2X LEVERAGE": {"date": "2026-05-25", "open": 11947.65, "high": 12060.55, "low": 11931.95, "close": 12038.15, "volume": 0}, "NIFTY100 QUALITY 30": {"date": "2026-05-25", "open": 5572.0, "high": 5577.65, "low": 5545.65, "close": 5554.1, "volume": 0}, "NIFTY200 ALPHA 30": {"date": "2026-05-25", "open": 25975.15, "high": 26203.6, "low": 25946.1, "close": 26143.75, "volume": 0}, "NIFTY MIDCAP150 MOMENTUM 50": {"date": "2026-05-25", "open": 63325.75, "high": 63535.45, "low": 63256.45, "close": 63431.9, "volume": 0}, "NIFTY SMALLCAP250 QUALITY 50": {"date": "2026-05-25", "open": 24818.55, "high": 25002.9, "low": 24794.9, "close": 24856.8, "volume": 0}, "NIFTY SMALLCAP250 MOMENTUM QUALITY 100": {"date": "2026-05-25", "open": 45380.05, "high": 45605.15, "low": 45306.25, "close": 45478.9, "volume": 0}, "NIFTY MIDSMALLCAP400 MOMENTUM QUALITY 100": {"date": "2026-05-25", "open": 50975.9, "high": 51074.1, "low": 50803.7, "close": 50953.65, "volume": 0}, "NIFTY500 MOMENTUM 50": {"date": "2026-05-25", "open": 53472.25, "high": 53719.8, "low": 53431.55, "close": 53637.2, "volume": 0}, "NIFTY200 VALUE 30": {"date": "2026-05-25", "open": 15564.1, "high": 15629.15, "low": 15530.9, "close": 15608.9, "volume": 0}, "NIFTY TOP 10 EQUAL WEIGHT": {"date": "2026-05-25", "open": 8633.45, "high": 8678.25, "low": 8622.05, "close": 8669.0, "volume": 0}, "NIFTY500 MULTICAP MOMENTUM QUALITY 50": {"date": "2026-05-25", "open": 42863.15, "high": 42949.3, "low": 42722.2, "close": 42892.05, "volume": 0}, "NIFTY TOP 15 EQUAL WEIGHT": {"date": "2026-05-25", "open": 9662.25, "high": 9714.15, "low": 9652.2, "close": 9702.8, "volume": 0}, "NIFTY TOP 20 EQUAL WEIGHT": {"date": "2026-05-25", "open": 8551.65, "high": 8597.95, "low": 8544.15, "close": 8586.7, "volume": 0}, "NIFTY500 QUALITY 50": {"date": "2026-05-25", "open": 19880.95, "high": 19887.0, "low": 19773.55, "close": 19791.6, "volume": 0}, "NIFTY500 LOW VOLATILITY 50": {"date": "2026-05-25", "open": 22264.95, "high": 22284.2, "low": 22173.4, "close": 22224.75, "volume": 0}, "NIFTY100 ESG": {"date": "2026-05-25", "open": 4852.65, "high": 4868.9, "low": 4847.35, "close": 4864.0, "volume": 0}, "NIFTY100 ENHANCED ESG": {"date": "2026-05-25", "open": 4885.9, "high": 4902.35, "low": 4880.55, "close": 4897.4, "volume": 0}, "NIFTY500 VALUE 50": {"date": "2026-05-25", "open": 16682.65, "high": 16710.5, "low": 16625.25, "close": 16691.3, "volume": 0}, "NIFTY100 ALPHA 30": {"date": "2026-05-25", "open": 17887.95, "high": 18009.55, "low": 17872.75, "close": 17988.8, "volume": 0}, "NIFTY500 MULTIFACTOR MQVLV 50": {"date": "2026-05-25", "open": 31213.75, "high": 31261.95, "low": 31083.25, "close": 31158.55, "volume": 0}, "NIFTY ALPHA LOW-VOLATILITY 30": {"date": "2026-05-25", "open": 26096.05, "high": 26235.05, "low": 26074.65, "close": 26201.45, "volume": 0}, "NIFTY500 FLEXICAP QUALITY 30": {"date": "2026-05-25", "open": 9747.9, "high": 9767.05, "low": 9717.0, "close": 9734.75, "volume": 0}, "NIFTY50 EQUAL WEIGHT": {"date": "2026-05-25", "open": 32735.6, "high": 32826.05, "low": 32671.2, "close": 32796.65, "volume": 0}, "NIFTY500 EQUAL WEIGHT": {"date": "2026-05-25", "open": 14328.95, "high": 14375.85, "low": 14319.0, "close": 14356.45, "volume": 0}, "NIFTY INDIA CORPORATE GROUP INDEX - TATA GROUP 25% CAP": {"date": "2026-05-25", "open": 14327.8, "high": 14389.1, "low": 14302.35, "close": 14362.95, "volume": 0}, "NIFTY PRIVATE BANK": {"date": "2026-05-25", "open": 26639.75, "high": 26978.3, "low": 26626.8, "close": 26927.1, "volume": 0}, "NIFTY SMALLCAP 250": {"date": "2026-05-25", "open": 16923.8, "high": 17000.25, "low": 16908.6, "close": 16976.4, "volume": 0}, "NIFTY SMALLCAP 50": {"date": "2026-05-25", "open": 8929.15, "high": 8987.85, "low": 8921.95, "close": 8977.9, "volume": 0}, "NIFTY MIDCAP 150": {"date": "2026-05-25", "open": 22703.35, "high": 22725.65, "low": 22645.75, "close": 22694.35, "volume": 0}, "NIFTY MIDCAP SELECT": {"date": "2026-05-25", "open": 14529.15, "high": 14577.35, "low": 14495.65, "close": 14559.9, "volume": 0}, "NIFTY LARGEMIDCAP 250": {"date": "2026-05-25", "open": 16446.95, "high": 16491.85, "low": 16426.1, "close": 16476.0, "volume": 0}, "NIFTY SME EMERGE": {"date": "2026-05-25", "open": 13747.05, "high": 13804.6, "low": 13737.7, "close": 13778.05, "volume": 0}, "NIFTY OIL & GAS": {"date": "2026-05-25", "open": 11512.35, "high": 11561.15, "low": 11483.95, "close": 11524.6, "volume": 0}, "NIFTY FINANCIAL SERVICES 25/50": {"date": "2026-05-25", "open": 28176.65, "high": 28537.95, "low": 28173.25, "close": 28493.15, "volume": 0}, "NIFTY HEALTHCARE INDEX": {"date": "2026-05-25", "open": 15698.8, "high": 15752.25, "low": 15638.85, "close": 15704.9, "volume": 0}, "NIFTY500 MULTICAP 50:25:25": {"date": "2026-05-25", "open": 16076.6, "high": 16133.35, "low": 16069.7, "close": 16120.2, "volume": 0}, "NIFTY MICROCAP 250": {"date": "2026-05-25", "open": 23489.2, "high": 23659.75, "low": 23443.65, "close": 23631.35, "volume": 0}, "NIFTY TOTAL MARKET": {"date": "2026-05-25", "open": 12868.15, "high": 12920.3, "low": 12862.65, "close": 12909.1, "volume": 0}, "NIFTY INDIA DIGITAL": {"date": "2026-05-25", "open": 7895.35, "high": 7904.7, "low": 7845.9, "close": 7862.45, "volume": 0}, "NIFTY MOBILITY": {"date": "2026-05-25", "open": 21611.85, "high": 21765.35, "low": 21580.35, "close": 21694.05, "volume": 0}, "NIFTY INDIA DEFENCE": {"date": "2026-05-25", "open": 9182.85, "high": 9264.6, "low": 9136.35, "close": 9219.65, "volume": 0}, "NIFTY FINANCIAL SERVICES EX-BANK": {"date": "2026-05-25", "open": 31841.65, "high": 32135.9, "low": 31813.0, "close": 32080.3, "volume": 0}, "NIFTY HOUSING": {"date": "2026-05-25", "open": 11992.3, "high": 12077.9, "low": 11971.3, "close": 12065.65, "volume": 0}, "NIFTY TRANSPORTATION & LOGISTICS": {"date": "2026-05-25", "open": 23892.15, "high": 24084.15, "low": 23870.35, "close": 23989.15, "volume": 0}, "NIFTY MIDSMALL FINANCIAL SERVICES": {"date": "2026-05-25", "open": 22289.75, "high": 22469.2, "low": 22269.9, "close": 22413.7, "volume": 0}, "NIFTY MIDSMALL HEALTHCARE": {"date": "2026-05-25", "open": 48498.85, "high": 48590.3, "low": 48284.4, "close": 48454.5, "volume": 0}, "NIFTY MIDSMALL IT & TELECOM": {"date": "2026-05-25", "open": 9346.65, "high": 9410.95, "low": 9271.35, "close": 9386.45, "volume": 0}, "NIFTY MIDSMALL INDIA CONSUMPTION": {"date": "2026-05-25", "open": 17987.05, "high": 17991.4, "low": 17786.9, "close": 17828.4, "volume": 0}, "NIFTY CORE HOUSING": {"date": "2026-05-25", "open": 15212.9, "high": 15242.05, "low": 15147.5, "close": 15215.25, "volume": 0}, "NIFTY500 MULTICAP INFRASTRUCTURE 50:30:20": {"date": "2026-05-25", "open": 14528.6, "high": 14555.0, "low": 14503.1, "close": 14546.6, "volume": 0}, "NIFTY RURAL": {"date": "2026-05-25", "open": 15276.2, "high": 15333.0, "low": 15257.3, "close": 15312.9, "volume": 0}, "NIFTY CAPITAL MARKETS": {"date": "2026-05-25", "open": 5615.85, "high": 5666.65, "low": 5593.6, "close": 5648.9, "volume": 0}, "NIFTY INDIA NEW AGE CONSUMPTION": {"date": "2026-05-25", "open": 11037.9, "high": 11068.5, "low": 11008.05, "close": 11031.35, "volume": 0}, "NIFTY INDIA SELECT 5 CORPORATE GROUPS (MAATR)": {"date": "2026-05-25", "open": 38739.9, "high": 38978.9, "low": 38629.4, "close": 38947.6, "volume": 0}, "NIFTY INDIA RAILWAYS PSU": {"date": "2026-05-25", "open": 3117.75, "high": 3138.25, "low": 3115.1, "close": 3132.25, "volume": 0}, "NIFTY CONSUMER DURABLES": {"date": "2026-05-25", "open": 35616.6, "high": 35769.1, "low": 35436.75, "close": 35671.05, "volume": 0}, "NIFTY NON-CYCLICAL CONSUMER": {"date": "2026-05-25", "open": 14835.3, "high": 14843.15, "low": 14730.0, "close": 14756.6, "volume": 0}, "NIFTY500 MULTICAP INDIA MANUFACTURING 50:30:20": {"date": "2026-05-25", "open": 16292.35, "high": 16352.4, "low": 16265.05, "close": 16340.75, "volume": 0}, "NIFTY EV & NEW AGE AUTOMOTIVE": {"date": "2026-05-25", "open": 3039.25, "high": 3057.05, "low": 3036.05, "close": 3050.7, "volume": 0}, "NIFTY500 LARGEMIDSMALL EQUAL-CAP WEIGHTED": {"date": "2026-05-25", "open": 17892.35, "high": 17946.55, "low": 17883.35, "close": 17932.7, "volume": 0}, "NIFTY INDIA TOURISM": {"date": "2026-05-25", "open": 7325.5, "high": 7371.15, "low": 7295.5, "close": 7356.6, "volume": 0}, "NIFTY MIDSMALLCAP 400": {"date": "2026-05-25", "open": 20568.1, "high": 20608.45, "low": 20537.1, "close": 20583.9, "volume": 0}, "NIFTY IPO": {"date": "2026-05-25", "open": 2088.95, "high": 2104.9, "low": 2087.95, "close": 2103.55, "volume": 0}, "NIFTY INDIA INTERNET": {"date": "2026-05-25", "open": 1224.1, "high": 1227.0, "low": 1217.5, "close": 1218.85, "volume": 0}, "NIFTY CHEMICALS": {"date": "2026-05-25", "open": 29445.0, "high": 29692.2, "low": 29304.2, "close": 29624.5, "volume": 0}, "NIFTY CONGLOMERATE 50": {"date": "2026-05-25", "open": 14680.9, "high": 14772.75, "low": 14660.0, "close": 14759.95, "volume": 0}, "NIFTY INDIA INFRASTRUCTURE & LOGISTICS": {"date": "2026-05-25", "open": 12111.75, "high": 12158.6, "low": 12082.55, "close": 12149.6, "volume": 0}, "NIFTY INDIA FPI 150": {"date": "2026-05-25", "open": 1546.1, "high": 1550.75, "low": 1543.7, "close": 1549.4, "volume": 0}, "NIFTY WAVES": {"date": "2026-05-25", "open": 1911.8, "high": 1923.3, "low": 1903.45, "close": 1914.85, "volume": 0}, "NIFTY SMALLCAP 500": {"date": "2026-05-25", "open": 19171.9, "high": 19268.85, "low": 19161.5, "close": 19247.8, "volume": 0}, "NIFTY CEMENT": {"date": "2026-05-25", "open": 15231.4, "high": 15326.0, "low": 15167.4, "close": 15241.8, "volume": 0}, "NIFTY REITS & REALTY": {"date": "2026-05-25", "open": 1793.0, "high": 1797.1, "low": 1787.65, "close": 1791.25, "volume": 0}, "NIFTY500 HEALTHCARE": {"date": "2026-05-25", "open": 20222.1, "high": 20273.55, "low": 20136.35, "close": 20223.7, "volume": 0}, "NIFTY MIDSMALLCAP400 50:50": {"date": "2026-05-25", "open": 19889.2, "high": 19940.2, "low": 19866.75, "close": 19915.75, "volume": 0}, "NIFTY TOTAL MARKET MOMENTUM QUALITY 50": {"date": "2026-05-25", "open": 44711.0, "high": 44779.35, "low": 44525.1, "close": 44709.35, "volume": 0}, "NIFTY100 LOW VOLATILITY 30": {"date": "2026-05-25", "open": 19792.55, "high": 19846.5, "low": 19776.75, "close": 19824.3, "volume": 0}, "NIFTY QUALITY LOW-VOLATILITY 30": {"date": "2026-05-25", "open": 16366.3, "high": 16392.55, "low": 16278.8, "close": 16315.0, "volume": 0}, "NIFTY ALPHA QUALITY LOW-VOLATILITY 30": {"date": "2026-05-25", "open": 22551.4, "high": 22625.15, "low": 22449.15, "close": 22499.0, "volume": 0}, "NIFTY ALPHA QUALITY VALUE LOW-VOLATILITY 30": {"date": "2026-05-25", "open": 20096.85, "high": 20131.35, "low": 20038.25, "close": 20090.6, "volume": 0}, "NIFTY200 QUALITY 30": {"date": "2026-05-25", "open": 20346.35, "high": 20360.7, "low": 20198.9, "close": 20210.55, "volume": 0}, "NIFTY MIDCAP150 QUALITY 50": {"date": "2026-05-25", "open": 23897.2, "high": 23939.5, "low": 23793.4, "close": 23823.0, "volume": 0}, "NIFTY200 MOMENTUM 30": {"date": "2026-05-25", "open": 30654.65, "high": 30847.45, "low": 30631.3, "close": 30801.0, "volume": 0}, "NIFTY INDIA MANUFACTURING": {"date": "2026-05-25", "open": 15935.75, "high": 15965.05, "low": 15894.8, "close": 15947.5, "volume": 0}, "NIFTY100 ESG SECTOR LEADERS": {"date": "2026-05-25", "open": 4007.55, "high": 4023.0, "low": 4001.0, "close": 4019.6, "volume": 0}, "NIFTY 8-13 YR G-SEC": {"date": "2026-05-25", "open": 2961.51, "high": 2974.76, "low": 2961.51, "close": 2973.94, "volume": 0}, "NIFTY 4-8 YR G-SEC INDEX": {"date": "2026-05-25", "open": 3238.18, "high": 3248.73, "low": 3238.18, "close": 3248.09, "volume": 0}, "NIFTY 11-15 YR G-SEC INDEX": {"date": "2026-05-25", "open": 3232.86, "high": 3251.58, "low": 3232.86, "close": 3249.57, "volume": 0}, "NIFTY 15 YR AND ABOVE G-SEC INDEX": {"date": "2026-05-25", "open": 3428.17, "high": 3447.21, "low": 3428.17, "close": 3446.53, "volume": 0}, "NIFTY COMPOSITE G-SEC INDEX": {"date": "2026-05-25", "open": 3040.9, "high": 3053.72, "low": 3040.9, "close": 3052.96, "volume": 0}, "NIFTY 10 YR BENCHMARK G-SEC": {"date": "2026-05-25", "open": 2595.85, "high": 2607.53, "low": 2595.84, "close": 2605.68, "volume": 0}, "NIFTY 10 YR BENCHMARK G-SEC (CLEAN PRICE)": {"date": "2026-05-25", "open": 862.03, "high": 865.92, "low": 862.03, "close": 865.31, "volume": 0}, "NIFTY BHARAT BOND INDEX - APRIL 2030": {"date": "2026-05-25", "open": 1565.65, "high": 1566.95, "low": 1565.65, "close": 1566.95, "volume": 0}, "NIFTY BHARAT BOND INDEX - APRIL 2031": {"date": "2026-05-25", "open": 1419.16, "high": 1420.41, "low": 1419.16, "close": 1420.41, "volume": 0}, "NIFTY BHARAT BOND INDEX - APRIL 2032": {"date": "2026-05-25", "open": 1284.65, "high": 1286.22, "low": 1284.65, "close": 1286.22, "volume": 0}, "NIFTY BHARAT BOND INDEX - APRIL 2033": {"date": "2026-05-25", "open": 1245.47, "high": 1247.28, "low": 1245.47, "close": 1247.28, "volume": 0}, "NIFTY50 USD": {"date": "2026-05-25", "open": 8586.35, "high": 8818.9, "low": 8544.25, "close": 8743.85, "volume": 0}}