{"NIFTY 50": {"date": "2026-02-20", "open": 25406.55, "high": 25663.55, "low": 25379.75, "close": 25571.25, "volume": 0}, "NIFTY NEXT 50": {"date": "2026-02-20", "open": 68913.2, "high": 69650.0, "low": 68862.25, "close": 69453.65, "volume": 0}, "NIFTY 100": {"date": "2026-02-20", "open": 26042.6, "high": 26307.4, "low": 26017.5, "close": 26217.3, "volume": 0}, "NIFTY 200": {"date": "2026-02-20", "open": 14184.4, "high": 14325.7, "low": 14172.2, "close": 14280.85, "volume": 0}, "NIFTY 500": {"date": "2026-02-20", "open": 23252.75, "high": 23467.4, "low": 23221.15, "close": 23395.0, "volume": 0}, "NIFTY MIDCAP 50": {"date": "2026-02-20", "open": 16811.35, "high": 16964.5, "low": 16783.85, "close": 16912.35, "volume": 0}, "NIFTY MIDCAP 100": {"date": "2026-02-20", "open": 59087.75, "high": 59690.5, "low": 58989.75, "close": 59513.95, "volume": 0}, "NIFTY SMALLCAP 100": {"date": "2026-02-20", "open": 16995.55, "high": 17087.6, "low": 16937.5, "close": 17002.15, "volume": 0}, "NIFTY AUTO": {"date": "2026-02-20", "open": 27734.7, "high": 27933.85, "low": 27617.45, "close": 27846.8, "volume": 0}, "NIFTY BANK": {"date": "2026-02-20", "open": 60627.85, "high": 61360.5, "low": 60562.35, "close": 61172.0, "volume": 0}, "NIFTY ENERGY": {"date": "2026-02-20", "open": 36092.0, "high": 36670.85, "low": 36089.35, "close": 36581.15, "volume": 0}, "NIFTY FINANCIAL SERVICES": {"date": "2026-02-20", "open": 28012.85, "high": 28299.35, "low": 27999.25, "close": 28210.6, "volume": 0}, "NIFTY FMCG": {"date": "2026-02-20", "open": 51443.85, "high": 51969.25, "low": 51401.45, "close": 51772.7, "volume": 0}, "NIFTY IT": {"date": "2026-02-20", "open": 32098.95, "high": 32339.8, "low": 31804.75, "close": 32004.05, "volume": 0}, "NIFTY MEDIA": {"date": "2026-02-20", "open": 1428.55, "high": 1437.75, "low": 1415.35, "close": 1426.8, "volume": 0}, "NIFTY METAL": {"date": "2026-02-20", "open": 11856.35, "high": 12029.6, "low": 11812.25, "close": 11989.95, "volume": 0}, "NIFTY MNC": {"date": "2026-02-20", "open": 30844.8, "high": 31319.45, "low": 30833.7, "close": 31211.5, "volume": 0}, "NIFTY PHARMA": {"date": "2026-02-20", "open": 22400.45, "high": 22515.0, "low": 22320.15, "close": 22452.4, "volume": 0}, "NIFTY PSU BANK": {"date": "2026-02-20", "open": 9493.25, "high": 9691.1, "low": 9470.5, "close": 9665.8, "volume": 0}, "NIFTY REALTY": {"date": "2026-02-20", "open": 814.15, "high": 824.1, "low": 812.0, "close": 820.7, "volume": 0}, "NIFTY INDIA CONSUMPTION": {"date": "2026-02-20", "open": 11659.75, "high": 11747.6, "low": 11630.55, "close": 11710.7, "volume": 0}, "NIFTY COMMODITIES": {"date": "2026-02-20", "open": 9794.5, "high": 9913.8, "low": 9780.0, "close": 9888.45, "volume": 0}, "NIFTY DIVIDEND OPPORTUNITIES 50": {"date": "2026-02-20", "open": 6283.5, "high": 6345.05, "low": 6271.9, "close": 6332.1, "volume": 0}, "NIFTY INFRASTRUCTURE": {"date": "2026-02-20", "open": 9539.65, "high": 9659.75, "low": 9539.3, "close": 9632.25, "volume": 0}, "NIFTY PSE": {"date": "2026-02-20", "open": 10241.9, "high": 10390.3, "low": 10237.4, "close": 10366.9, "volume": 0}, "NIFTY SERVICES SECTOR": {"date": "2026-02-20", "open": 32828.8, "high": 33110.15, "low": 32780.75, "close": 32981.05, "volume": 0}, "NIFTY50 SHARIAH": {"date": "2026-02-20", "open": 4486.5, "high": 4529.75, "low": 4468.35, "close": 4512.65, "volume": 0}, "NIFTY500 SHARIAH": {"date": "2026-02-20", "open": 6837.8, "high": 6896.25, "low": 6816.0, "close": 6879.25, "volume": 0}, "NIFTY LOW VOLATILITY 50": {"date": "2026-02-20", "open": 25168.55, "high": 25400.25, "low": 25118.45, "close": 25319.0, "volume": 0}, "NIFTY ALPHA 50": {"date": "2026-02-20", "open": 50583.0, "high": 51212.65, "low": 50463.0, "close": 51047.1, "volume": 0}, "NIFTY HIGH BETA 50": {"date": "2026-02-20", "open": 3798.5, "high": 3838.75, "low": 3793.0, "close": 3820.1, "volume": 0}, "NIFTY100 EQUAL WEIGHT": {"date": "2026-02-20", "open": 33715.9, "high": 34100.95, "low": 33687.5, "close": 33989.0, "volume": 0}, "NIFTY100 LIQUID 15": {"date": "2026-02-20", "open": 7607.1, "high": 7692.25, "low": 7587.7, "close": 7660.4, "volume": 0}, "NIFTY CPSE": {"date": "2026-02-20", "open": 6927.7, "high": 7034.65, "low": 6922.55, "close": 7022.35, "volume": 0}, "NIFTY50 VALUE 20": {"date": "2026-02-20", "open": 12962.45, "high": 13091.25, "low": 12936.45, "close": 13058.75, "volume": 0}, "NIFTY MIDCAP LIQUID 15": {"date": "2026-02-20", "open": 15359.0, "high": 15499.2, "low": 15330.55, "close": 15384.15, "volume": 0}, "NIFTY SHARIAH 25": {"date": "2026-02-20", "open": 7954.45, "high": 8034.4, "low": 7940.25, "close": 8004.55, "volume": 0}, "INDIA VIX": {"date": "2026-02-20", "open": 13.46, "high": 14.7825, "low": 13.095, "close": 14.36, "volume": 0}, "NIFTY GROWTH SECTORS 15": {"date": "2026-02-20", "open": 11480.1, "high": 11541.75, "low": 11423.0, "close": 11509.55, "volume": 0}, "NIFTY50 TR 1X INVERSE": {"date": "2026-02-20", "open": 168.9, "high": 169.1, "low": 167.2, "close": 167.8, "volume": 0}, "NIFTY50 TR 2X LEVERAGE": {"date": "2026-02-20", "open": 20647.6, "high": 21065.85, "low": 20605.0, "close": 20915.9, "volume": 0}, "NIFTY50 PR 1X INVERSE": {"date": "2026-02-20", "open": 206.65, "high": 206.85, "low": 204.55, "close": 205.3, "volume": 0}, "NIFTY50 PR 2X LEVERAGE": {"date": "2026-02-20", "open": 13768.4, "high": 14047.3, "low": 13739.95, "close": 13947.25, "volume": 0}, "NIFTY100 QUALITY 30": {"date": "2026-02-20", "open": 5579.7, "high": 5640.6, "low": 5574.05, "close": 5612.85, "volume": 0}, "NIFTY MIDCAP150 QUALITY 50": {"date": "2026-02-20", "open": 23248.05, "high": 23487.75, "low": 23174.75, "close": 23405.2, "volume": 0}, "NIFTY200 MOMENTUM 30": {"date": "2026-02-20", "open": 31248.95, "high": 31663.75, "low": 31208.1, "close": 31588.8, "volume": 0}, "NIFTY INDIA MANUFACTURING": {"date": "2026-02-20", "open": 15512.0, "high": 15680.4, "low": 15494.1, "close": 15631.25, "volume": 0}, "NIFTY100 ESG SECTOR LEADERS": {"date": "2026-02-20", "open": 4189.35, "high": 4228.6, "low": 4180.55, "close": 4211.7, "volume": 0}, "NIFTY200 ALPHA 30": {"date": "2026-02-20", "open": 25352.55, "high": 25702.95, "low": 25310.85, "close": 25621.75, "volume": 0}, "NIFTY MIDCAP150 MOMENTUM 50": {"date": "2026-02-20", "open": 61661.6, "high": 62382.15, "low": 61523.5, "close": 62190.8, "volume": 0}, "NIFTY SMALLCAP250 QUALITY 50": {"date": "2026-02-20", "open": 24312.55, "high": 24416.05, "low": 24176.7, "close": 24306.5, "volume": 0}, "NIFTY SMALLCAP250 MOMENTUM QUALITY 100": {"date": "2026-02-20", "open": 42011.35, "high": 42226.0, "low": 41830.85, "close": 42084.2, "volume": 0}, "NIFTY MIDSMALLCAP400 MOMENTUM QUALITY 100": {"date": "2026-02-20", "open": 46707.3, "high": 47138.9, "low": 46616.4, "close": 47008.6, "volume": 0}, "NIFTY500 MOMENTUM 50": {"date": "2026-02-20", "open": 52115.05, "high": 52713.8, "low": 52025.0, "close": 52568.65, "volume": 0}, "NIFTY TOP 10 EQUAL WEIGHT": {"date": "2026-02-20", "open": 9390.0, "high": 9499.7, "low": 9384.1, "close": 9464.15, "volume": 0}, "NIFTY500 MULTICAP MOMENTUM QUALITY 50": {"date": "2026-02-20", "open": 40448.6, "high": 40874.05, "low": 40382.45, "close": 40741.0, "volume": 0}, "NIFTY TOP 15 EQUAL WEIGHT": {"date": "2026-02-20", "open": 10617.5, "high": 10732.6, "low": 10605.35, "close": 10696.0, "volume": 0}, "NIFTY TOP 20 EQUAL WEIGHT": {"date": "2026-02-20", "open": 9361.5, "high": 9452.75, "low": 9347.25, "close": 9420.35, "volume": 0}, "NIFTY500 QUALITY 50": {"date": "2026-02-20", "open": 18333.85, "high": 18515.65, "low": 18292.1, "close": 18436.1, "volume": 0}, "NIFTY500 LOW VOLATILITY 50": {"date": "2026-02-20", "open": 22799.95, "high": 23007.55, "low": 22752.5, "close": 22947.3, "volume": 0}, "NIFTY100 ESG": {"date": "2026-02-20", "open": 5064.95, "high": 5114.05, "low": 5053.85, "close": 5095.25, "volume": 0}, "NIFTY100 ENHANCED ESG": {"date": "2026-02-20", "open": 5103.7, "high": 5153.15, "low": 5092.35, "close": 5134.1, "volume": 0}, "NIFTY500 VALUE 50": {"date": "2026-02-20", "open": 16430.3, "high": 16620.45, "low": 16413.15, "close": 16585.45, "volume": 0}, "NIFTY100 ALPHA 30": {"date": "2026-02-20", "open": 18087.25, "high": 18290.25, "low": 18049.4, "close": 18228.4, "volume": 0}, "NIFTY500 MULTIFACTOR MQVLV 50": {"date": "2026-02-20", "open": 31758.25, "high": 32097.2, "low": 31728.75, "close": 32029.3, "volume": 0}, "NIFTY ALPHA LOW-VOLATILITY 30": {"date": "2026-02-20", "open": 27248.7, "high": 27480.15, "low": 27175.0, "close": 27402.4, "volume": 0}, "NIFTY50 EQUAL WEIGHT": {"date": "2026-02-20", "open": 33113.25, "high": 33469.05, "low": 33061.65, "close": 33356.05, "volume": 0}, "NIFTY500 EQUAL WEIGHT": {"date": "2026-02-20", "open": 13770.9, "high": 13853.7, "low": 13717.05, "close": 13816.05, "volume": 0}, "NIFTY INDIA CORPORATE GROUP INDEX - TATA GROUP 25% CAP": {"date": "2026-02-20", "open": 14938.05, "high": 15113.65, "low": 14901.05, "close": 15061.9, "volume": 0}, "NIFTY PRIVATE BANK": {"date": "2026-02-20", "open": 28695.8, "high": 29029.15, "low": 28689.35, "close": 28908.6, "volume": 0}, "NIFTY SMALLCAP 250": {"date": "2026-02-20", "open": 15958.8, "high": 16018.2, "low": 15880.9, "close": 15958.8, "volume": 0}, "NIFTY SMALLCAP 50": {"date": "2026-02-20", "open": 8324.7, "high": 8369.35, "low": 8301.5, "close": 8333.65, "volume": 0}, "NIFTY MIDCAP 150": {"date": "2026-02-20", "open": 21764.55, "high": 21981.75, "low": 21726.95, "close": 21918.2, "volume": 0}, "NIFTY MIDCAP SELECT": {"date": "2026-02-20", "open": 13407.55, "high": 13526.0, "low": 13382.85, "close": 13476.0, "volume": 0}, "NIFTY LARGEMIDCAP 250": {"date": "2026-02-20", "open": 16456.95, "high": 16615.9, "low": 16437.5, "close": 16570.25, "volume": 0}, "NIFTY SME EMERGE": {"date": "2026-02-20", "open": 13114.7, "high": 13126.15, "low": 13062.2, "close": 13073.03, "volume": 0}, "NIFTY OIL & GAS": {"date": "2026-02-20", "open": 12033.75, "high": 12120.75, "low": 12014.95, "close": 12092.3, "volume": 0}, "NIFTY FINANCIAL SERVICES 25/50": {"date": "2026-02-20", "open": 30424.1, "high": 30685.25, "low": 30399.65, "close": 30596.5, "volume": 0}, "NIFTY HEALTHCARE INDEX": {"date": "2026-02-20", "open": 14494.6, "high": 14592.7, "low": 14466.2, "close": 14560.75, "volume": 0}, "NIFTY500 MULTICAP 50:25:25": {"date": "2026-02-20", "open": 16011.25, "high": 16140.95, "low": 15980.05, "close": 16093.65, "volume": 0}, "NIFTY MICROCAP 250": {"date": "2026-02-20", "open": 21686.85, "high": 21742.9, "low": 21537.9, "close": 21679.05, "volume": 0}, "NIFTY TOTAL MARKET": {"date": "2026-02-20", "open": 13040.7, "high": 13157.9, "low": 13020.4, "close": 13117.4, "volume": 0}, "NIFTY INDIA DIGITAL": {"date": "2026-02-20", "open": 8270.25, "high": 8328.4, "low": 8237.3, "close": 8270.8, "volume": 0}, "NIFTY MOBILITY": {"date": "2026-02-20", "open": 22752.65, "high": 22939.2, "low": 22693.8, "close": 22896.45, "volume": 0}, "NIFTY INDIA DEFENCE": {"date": "2026-02-20", "open": 8021.05, "high": 8205.6, "low": 7999.45, "close": 8099.45, "volume": 0}, "NIFTY FINANCIAL SERVICES EX-BANK": {"date": "2026-02-20", "open": 31642.75, "high": 31964.3, "low": 31566.85, "close": 31857.4, "volume": 0}, "NIFTY HOUSING": {"date": "2026-02-20", "open": 11947.9, "high": 12123.75, "low": 11938.45, "close": 12086.45, "volume": 0}, "NIFTY TRANSPORTATION & LOGISTICS": {"date": "2026-02-20", "open": 25231.05, "high": 25410.15, "low": 25139.6, "close": 25341.5, "volume": 0}, "NIFTY MIDSMALL FINANCIAL SERVICES": {"date": "2026-02-20", "open": 20739.2, "high": 20959.45, "low": 20692.15, "close": 20880.45, "volume": 0}, "NIFTY MIDSMALL HEALTHCARE": {"date": "2026-02-20", "open": 42571.05, "high": 42790.45, "low": 42364.0, "close": 42563.4, "volume": 0}, "NIFTY MIDSMALL IT & TELECOM": {"date": "2026-02-20", "open": 8999.0, "high": 9072.8, "low": 8916.85, "close": 8972.4, "volume": 0}, "NIFTY MIDSMALL INDIA CONSUMPTION": {"date": "2026-02-20", "open": 18062.25, "high": 18246.5, "low": 18047.85, "close": 18172.45, "volume": 0}, "NIFTY CORE HOUSING": {"date": "2026-02-20", "open": 15172.45, "high": 15333.3, "low": 15137.35, "close": 15276.95, "volume": 0}, "NIFTY500 MULTICAP INFRASTRUCTURE 50:30:20": {"date": "2026-02-20", "open": 14154.2, "high": 14313.45, "low": 14145.1, "close": 14275.7, "volume": 0}, "NIFTY RURAL": {"date": "2026-02-20", "open": 16076.8, "high": 16236.35, "low": 16039.85, "close": 16191.0, "volume": 0}, "NIFTY CAPITAL MARKETS": {"date": "2026-02-20", "open": 4665.75, "high": 4706.85, "low": 4659.15, "close": 4671.6, "volume": 0}, "NIFTY INDIA NEW AGE CONSUMPTION": {"date": "2026-02-20", "open": 11313.45, "high": 11398.45, "low": 11289.45, "close": 11366.2, "volume": 0}, "NIFTY INDIA SELECT 5 CORPORATE GROUPS (MAATR)": {"date": "2026-02-20", "open": 37390.55, "high": 37707.75, "low": 37255.5, "close": 37523.65, "volume": 0}, "NIFTY INDIA RAILWAYS PSU": {"date": "2026-02-20", "open": 3272.45, "high": 3327.15, "low": 3267.45, "close": 3313.55, "volume": 0}, "NIFTY CONSUMER DURABLES": {"date": "2026-02-20", "open": 37399.85, "high": 37743.3, "low": 37364.55, "close": 37588.35, "volume": 0}, "NIFTY NON-CYCLICAL CONSUMER": {"date": "2026-02-20", "open": 15153.6, "high": 15300.15, "low": 15133.5, "close": 15239.65, "volume": 0}, "NIFTY500 MULTICAP INDIA MANUFACTURING 50:30:20": {"date": "2026-02-20", "open": 15694.55, "high": 15840.0, "low": 15657.7, "close": 15792.6, "volume": 0}, "NIFTY EV & NEW AGE AUTOMOTIVE": {"date": "2026-02-20", "open": 3031.1, "high": 3067.85, "low": 3021.9, "close": 3060.3, "volume": 0}, "NIFTY500 LARGEMIDSMALL EQUAL-CAP WEIGHTED": {"date": "2026-02-20", "open": 17540.0, "high": 17670.0, "low": 17499.8, "close": 17621.05, "volume": 0}, "NIFTY INDIA TOURISM": {"date": "2026-02-20", "open": 7908.25, "high": 8003.1, "low": 7889.25, "close": 7965.3, "volume": 0}, "NIFTY MIDSMALLCAP 400": {"date": "2026-02-20", "open": 19610.35, "high": 19755.8, "low": 19563.0, "close": 19702.0, "volume": 0}, "NIFTY IPO": {"date": "2026-02-20", "open": 1966.55, "high": 1974.15, "low": 1953.5, "close": 1956.6, "volume": 0}, "NIFTY INDIA INTERNET": {"date": "2026-02-20", "open": 1249.4, "high": 1260.4, "low": 1248.95, "close": 1252.95, "volume": 0}, "NIFTY CHEMICALS": {"date": "2026-02-20", "open": 28420.0, "high": 28588.85, "low": 28358.35, "close": 28450.5, "volume": 0}, "NIFTY CONGLOMERATE 50": {"date": "2026-02-20", "open": 14688.85, "high": 14862.85, "low": 14654.95, "close": 14808.9, "volume": 0}, "NIFTY INDIA INFRASTRUCTURE & LOGISTICS": {"date": "2026-02-20", "open": 11367.2, "high": 11539.5, "low": 11365.2, "close": 11500.05, "volume": 0}, "NIFTY INDIA FPI 150": {"date": "2026-02-20", "open": 1571.25, "high": 1586.1, "low": 1568.95, "close": 1580.85, "volume": 0}, "NIFTY WAVES": {"date": "2026-02-20", "open": 1957.15, "high": 1964.5, "low": 1949.25, "close": 1951.5, "volume": 0}, "NIFTY500 HEALTHCARE": {"date": "2026-02-20", "open": 18410.2, "high": 18503.05, "low": 18344.15, "close": 18458.35, "volume": 0}, "NIFTY200 VALUE 30": {"date": "2026-02-20", "open": 15672.65, "high": 15879.9, "low": 15666.15, "close": 15844.1, "volume": 0}, "NIFTY TOTAL MARKET MOMENTUM QUALITY 50": {"date": "2026-02-20", "open": 41651.5, "high": 42126.55, "low": 41577.7, "close": 42011.9, "volume": 0}, "NIFTY500 FLEXICAP QUALITY 30": {"date": "2026-02-20", "open": 9919.7, "high": 10025.55, "low": 9897.75, "close": 9977.0, "volume": 0}, "NIFTY100 LOW VOLATILITY 30": {"date": "2026-02-20", "open": 20518.85, "high": 20724.2, "low": 20483.7, "close": 20671.75, "volume": 0}, "NIFTY QUALITY LOW-VOLATILITY 30": {"date": "2026-02-20", "open": 16835.05, "high": 16995.3, "low": 16817.4, "close": 16950.0, "volume": 0}, "NIFTY ALPHA QUALITY LOW-VOLATILITY 30": {"date": "2026-02-20", "open": 22527.3, "high": 22750.5, "low": 22491.2, "close": 22675.45, "volume": 0}, "NIFTY ALPHA QUALITY VALUE LOW-VOLATILITY 30": {"date": "2026-02-20", "open": 20598.05, "high": 20797.8, "low": 20577.4, "close": 20731.8, "volume": 0}, "NIFTY200 QUALITY 30": {"date": "2026-02-20", "open": 20238.5, "high": 20434.4, "low": 20205.35, "close": 20363.8, "volume": 0}, "NIFTY 8-13 YR G-SEC": {"date": "2026-02-20", "open": 2986.67, "high": 2986.68, "low": 2975.66, "close": 2978.8, "volume": 0}, "NIFTY 4-8 YR G-SEC INDEX": {"date": "2026-02-20", "open": 3253.43, "high": 3253.74, "low": 3247.49, "close": 3248.15, "volume": 0}, "NIFTY 11-15 YR G-SEC INDEX": {"date": "2026-02-20", "open": 3264.88, "high": 3264.88, "low": 3255.56, "close": 3255.68, "volume": 0}, "NIFTY 15 YR AND ABOVE G-SEC INDEX": {"date": "2026-02-20", "open": 3467.93, "high": 3467.93, "low": 3449.98, "close": 3461.93, "volume": 0}, "NIFTY COMPOSITE G-SEC INDEX": {"date": "2026-02-20", "open": 3063.53, "high": 3063.59, "low": 3053.09, "close": 3056.44, "volume": 0}, "NIFTY 10 YR BENCHMARK G-SEC": {"date": "2026-02-20", "open": 2623.1, "high": 2623.11, "low": 2612.95, "close": 2615.51, "volume": 0}, "NIFTY 10 YR BENCHMARK G-SEC (CLEAN PRICE)": {"date": "2026-02-20", "open": 887.23, "high": 887.24, "low": 883.72, "close": 884.6, "volume": 0}, "NIFTY BHARAT BOND INDEX - APRIL 2030": {"date": "2026-02-20", "open": 1573.22, "high": 1573.22, "low": 1572.75, "close": 1572.75, "volume": 0}, "NIFTY BHARAT BOND INDEX - APRIL 2031": {"date": "2026-02-20", "open": 1429.86, "high": 1430.19, "low": 1429.86, "close": 1430.14, "volume": 0}, "NIFTY BHARAT BOND INDEX - APRIL 2032": {"date": "2026-02-20", "open": 1300.5, "high": 1301.27, "low": 1300.5, "close": 1300.88, "volume": 0}, "NIFTY BHARAT BOND INDEX - APRIL 2033": {"date": "2026-02-20", "open": 1262.95, "high": 1262.95, "low": 1262.09, "close": 1262.09, "volume": 0}, "NIFTY50 USD": {"date": "2026-02-20", "open": 9726.7, "high": 9775.4, "low": 9524.35, "close": 9737.82, "volume": 0}}